[
  {
    "end_time": 8980,
    "index": 1,
    "start_time": 600,
    "text": "Loving can hurt\nLoving can hurt sometimes"
  },
  {
    "end_time": 22320,
    "index": 2,
    "start_time": 8990,
    "text": "But it&#39;s the only thing that I know\nWhen it gets hard"
  },
  {
    "end_time": 33840,
    "index": 3,
    "start_time": 22320,
    "text": "You know it can get hard sometimes\nIt is the only thing that makes us feel alive"
  },
  {
    "end_time": 46030,
    "index": 4,
    "start_time": 37649,
    "text": "We keep this love in a photograph\nWe made these memories for ourselves"
  },
  {
    "end_time": 51129,
    "index": 5,
    "start_time": 46030,
    "text": "Where our eyes are never closing\nHearts are never broken"
  },
  {
    "end_time": 54800,
    "index": 6,
    "start_time": 51129,
    "text": "Times forever frozen still"
  },
  {
    "end_time": 58828,
    "index": 7,
    "start_time": 54800,
    "text": "So you can keep me\nInside the pocket"
  },
  {
    "end_time": 63960,
    "index": 8,
    "start_time": 58829,
    "text": "Of your ripped jeans\nHoldin&#39; me closer"
  },
  {
    "end_time": 71469,
    "index": 9,
    "start_time": 63960,
    "text": "&#39;Til our eyes meet\nYou won&#39;t ever be alone"
  },
  {
    "end_time": 74749,
    "index": 10,
    "start_time": 71469,
    "text": "Wait for me to come home"
  },
  {
    "end_time": 86280,
    "index": 11,
    "start_time": 77350,
    "text": "Loving can heal\nLoving can mend your soul"
  },
  {
    "end_time": 97880,
    "index": 12,
    "start_time": 86280,
    "text": "And it&#39;s the only thing that I know, know\nI swear it will get easier"
  },
  {
    "end_time": 108240,
    "index": 13,
    "start_time": 98640,
    "text": "Remember that with every piece of you\nAnd it&#39;s the only thing we take with us when"
  },
  {
    "end_time": 111520,
    "index": 14,
    "start_time": 108240,
    "text": "we die"
  },
  {
    "end_time": 121658,
    "index": 15,
    "start_time": 114960,
    "text": "We keep this love in this photograph\nWe made these memories for ourselves"
  },
  {
    "end_time": 127759,
    "index": 16,
    "start_time": 122800,
    "text": "Where our eyes are never closing\nOur hearts were never broken"
  },
  {
    "end_time": 130209,
    "index": 17,
    "start_time": 127770,
    "text": "Times forever frozen still"
  },
  {
    "end_time": 133740,
    "index": 18,
    "start_time": 131460,
    "text": "So you can keep me"
  },
  {
    "end_time": 140000,
    "index": 19,
    "start_time": 134880,
    "text": "Inside the pocket of your ripped jeans\nHoldin&#39; me closer"
  },
  {
    "end_time": 149440,
    "index": 20,
    "start_time": 140160,
    "text": "&#39;Til our eyes meet\nYou won&#39;t ever be alone"
  },
  {
    "end_time": 157280,
    "index": 21,
    "start_time": 149600,
    "text": "And if you hurt me\nThat&#39;s OK, baby, only words bleed"
  },
  {
    "end_time": 166560,
    "index": 22,
    "start_time": 157280,
    "text": "Inside these pages you just hold me\nAnd I won&#39;t ever let you go"
  },
  {
    "end_time": 175360,
    "index": 23,
    "start_time": 166560,
    "text": "Wait for me to come home\nWait for me to come home"
  },
  {
    "end_time": 186160,
    "index": 24,
    "start_time": 176640,
    "text": "Wait for me to come home\nWait for me to come home"
  },
  {
    "end_time": 191240,
    "index": 25,
    "start_time": 186240,
    "text": "Oh you can fit me\nInside the necklace you got when you were"
  },
  {
    "end_time": 195080,
    "index": 26,
    "start_time": 191240,
    "text": "sixteen\nNext to your heartbeat"
  },
  {
    "end_time": 203480,
    "index": 27,
    "start_time": 195080,
    "text": "Where I should be\nKeep it deep within your soul"
  },
  {
    "end_time": 211120,
    "index": 28,
    "start_time": 204080,
    "text": "And if you hurt me\nWell, that&#39;s OK, baby, only words bleed"
  },
  {
    "end_time": 221240,
    "index": 29,
    "start_time": 211120,
    "text": "Inside these pages you just hold me\nAnd I won&#39;t ever let you go"
  },
  {
    "end_time": 229600,
    "index": 30,
    "start_time": 222080,
    "text": "When I&#39;m away\nI will remember how you kissed me"
  },
  {
    "end_time": 234279,
    "index": 31,
    "start_time": 229640,
    "text": "Under the lamppost\nBack on 6th street"
  },
  {
    "end_time": 241200,
    "index": 32,
    "start_time": 234280,
    "text": "Hearing you whisper through the phone,\n&quot;Wait for me to come home.&quot;"
  }
]