[
    {
        "index": 1,
        "start_time": 4935,
        "end_time": 8563,
        "text": "StoryCorps Founder &amp; TED Prize winner\nDavey Isay has created an app that aims"
    },
    {
        "index": 2,
        "start_time": 8563,
        "end_time": 12340,
        "text": "to bring people together in a project of \nlistening, connection, and generosity."
    },
    {
        "index": 3,
        "start_time": 12340,
        "end_time": 13136,
        "text": "Here&#39;s why..."
    },
    {
        "index": 4,
        "start_time": 13136,
        "end_time": 16545,
        "text": "This is the library of lost stories."
    },
    {
        "index": 5,
        "start_time": 16545,
        "end_time": 20721,
        "text": "It&#39;s where you&#39;ll find the true origins\nof the Sphinx and Stonehenge,"
    },
    {
        "index": 6,
        "start_time": 20721,
        "end_time": 23388,
        "text": "the text lost in the fire of Alexandria,"
    },
    {
        "index": 7,
        "start_time": 23388,
        "end_time": 27820,
        "text": "all of the great ideas \nthat Einstein never thought to write down,"
    },
    {
        "index": 8,
        "start_time": 27820,
        "end_time": 32124,
        "text": "the dream you can&#39;t quite \nremember from last night,"
    },
    {
        "index": 9,
        "start_time": 32124,
        "end_time": 34750,
        "text": "your ancestor&#39;s first words,"
    },
    {
        "index": 10,
        "start_time": 34750,
        "end_time": 41660,
        "text": "her last words."
    },
    {
        "index": 11,
        "start_time": 41660,
        "end_time": 44803,
        "text": "And it&#39;s the fastest growing library\nin the world."
    },
    {
        "index": 12,
        "start_time": 44803,
        "end_time": 46611,
        "text": "In the next year,"
    },
    {
        "index": 13,
        "start_time": 46611,
        "end_time": 49885,
        "text": "25 languages will be added\nto the collection,"
    },
    {
        "index": 14,
        "start_time": 49885,
        "end_time": 53317,
        "text": "never to be heard aloud again,"
    },
    {
        "index": 15,
        "start_time": 53317,
        "end_time": 57853,
        "text": "50 million points of view\nnever related,"
    },
    {
        "index": 16,
        "start_time": 57853,
        "end_time": 63311,
        "text": "the last eyewitness account\nof an incredible act of athleticism,"
    },
    {
        "index": 17,
        "start_time": 63311,
        "end_time": 64661,
        "text": "disobedience,"
    },
    {
        "index": 18,
        "start_time": 64661,
        "end_time": 66292,
        "text": "courage,"
    },
    {
        "index": 19,
        "start_time": 66292,
        "end_time": 67478,
        "text": "unread,"
    },
    {
        "index": 20,
        "start_time": 67478,
        "end_time": 69078,
        "text": "unheard,"
    },
    {
        "index": 21,
        "start_time": 69078,
        "end_time": 75448,
        "text": "unwatched."
    },
    {
        "index": 22,
        "start_time": 75448,
        "end_time": 80135,
        "text": "But this is the StoryCorps archive\nat the Library of Congress"
    },
    {
        "index": 23,
        "start_time": 80135,
        "end_time": 85464,
        "text": "where everything recorded by StoryCorps\nis preserved for posterity."
    },
    {
        "index": 24,
        "start_time": 85464,
        "end_time": 86743,
        "text": "This is where,"
    },
    {
        "index": 25,
        "start_time": 86743,
        "end_time": 88444,
        "text": "if you record your parents,"
    },
    {
        "index": 26,
        "start_time": 88444,
        "end_time": 89638,
        "text": "your grandparents,"
    },
    {
        "index": 27,
        "start_time": 89638,
        "end_time": 90924,
        "text": "your neighbors,"
    },
    {
        "index": 28,
        "start_time": 90924,
        "end_time": 92942,
        "text": "your children,"
    },
    {
        "index": 29,
        "start_time": 92942,
        "end_time": 97052,
        "text": "their stories will live on."
    },
    {
        "index": 30,
        "start_time": 97052,
        "end_time": 103929,
        "text": "What if Anne Frank hadn&#39;t kept her diary?"
    },
    {
        "index": 31,
        "start_time": 103929,
        "end_time": 108272,
        "text": "What if no one could listen to\nMartin Luther King&#39;s Mountaintop speech?"
    },
    {
        "index": 32,
        "start_time": 108272,
        "end_time": 118199,
        "text": "What if the camera hadn&#39;t been rolling\nduring the first moon landing?"
    },
    {
        "index": 33,
        "start_time": 118199,
        "end_time": 120994,
        "text": "But what if, this Thanksgiving,"
    },
    {
        "index": 34,
        "start_time": 120994,
        "end_time": 126149,
        "text": "the youngest member of every family\ninterviewed the oldest?"
    },
    {
        "index": 35,
        "start_time": 126149,
        "end_time": 130616,
        "text": "&quot;It&#39;s like the only thing on his mind\nwas to tell the kids that he loved them.&quot;"
    },
    {
        "index": 36,
        "start_time": 130616,
        "end_time": 136268,
        "text": "Or if on February 14th, you asked a person\nyou love some questions"
    },
    {
        "index": 37,
        "start_time": 136268,
        "end_time": 138841,
        "text": "you&#39;ve never thought to ask."
    },
    {
        "index": 38,
        "start_time": 138841,
        "end_time": 141371,
        "text": "&quot;Being married is like having\na color television set,"
    },
    {
        "index": 39,
        "start_time": 141371,
        "end_time": 143585,
        "text": "you never want to go back \nto black and white.&quot;"
    },
    {
        "index": 40,
        "start_time": 143585,
        "end_time": 146125,
        "text": "History is all of these things,"
    },
    {
        "index": 41,
        "start_time": 146125,
        "end_time": 148078,
        "text": "the testament to tragedy,"
    },
    {
        "index": 42,
        "start_time": 148078,
        "end_time": 150171,
        "text": "the progress of civilization,"
    },
    {
        "index": 43,
        "start_time": 150171,
        "end_time": 152032,
        "text": "the heroic triumphs,"
    },
    {
        "index": 44,
        "start_time": 152032,
        "end_time": 156827,
        "text": "and the moments and stories\nthat are our lives."
    },
    {
        "index": 45,
        "start_time": 156827,
        "end_time": 161511,
        "text": "It&#39;s also the act of actively listening\nto the voices of the past"
    },
    {
        "index": 46,
        "start_time": 161511,
        "end_time": 164150,
        "text": "and the people who matter to us."
    },
    {
        "index": 47,
        "start_time": 164150,
        "end_time": 166746,
        "text": "&quot;Grand Central Station, now,"
    },
    {
        "index": 48,
        "start_time": 166746,
        "end_time": 170728,
        "text": "we know there&#39;s an architect, \nbut who hung the iron?"
    },
    {
        "index": 49,
        "start_time": 170728,
        "end_time": 173908,
        "text": "Who were the brick masons?"
    },
    {
        "index": 50,
        "start_time": 173908,
        "end_time": 176126,
        "text": "Who swept the floor?"
    },
    {
        "index": 51,
        "start_time": 176126,
        "end_time": 178721,
        "text": "Who kept the trains going?"
    },
    {
        "index": 52,
        "start_time": 178721,
        "end_time": 182992,
        "text": "We shall begin celebrating the lives\nof the uncelebrated.&quot;"
    },
    {
        "index": 53,
        "start_time": 182992,
        "end_time": 187455,
        "text": "So you can make history\nby recording it."
    }
]