[
  {
    "end_time": 5580,
    "index": 1,
    "start_time": 853,
    "text": "(humming rhythmic song)"
  },
  {
    "end_time": 14061,
    "index": 2,
    "start_time": 10888,
    "text": "- I don&#39;t really know much about tuxedos"
  },
  {
    "end_time": 16254,
    "index": 3,
    "start_time": 14061,
    "text": "except for that penguins wear them."
  },
  {
    "end_time": 17526,
    "index": 4,
    "start_time": 16254,
    "text": "- I don&#39;t know. I feel indifferent."
  },
  {
    "end_time": 20005,
    "index": 5,
    "start_time": 17526,
    "text": "- Normally, I would be concerned"
  },
  {
    "end_time": 23320,
    "index": 6,
    "start_time": 20005,
    "text": "that I&#39;m not gonna be\nable to move my arms,"
  },
  {
    "end_time": 24662,
    "index": 7,
    "start_time": 23321,
    "text": "because my shoulders will get stuck,"
  },
  {
    "end_time": 26787,
    "index": 8,
    "start_time": 24662,
    "text": "but because this is a men&#39;s suit,"
  },
  {
    "end_time": 28718,
    "index": 9,
    "start_time": 26787,
    "text": "I have a feeling it might\nfit my shoulders better."
  },
  {
    "end_time": 31847,
    "index": 10,
    "start_time": 28719,
    "text": "- No one in my family\nreally wears tuxes or suits."
  },
  {
    "end_time": 34110,
    "index": 11,
    "start_time": 31847,
    "text": "I just imagine that anything has to be"
  },
  {
    "end_time": 37586,
    "index": 12,
    "start_time": 34110,
    "text": "more comfortable than what women wear."
  },
  {
    "end_time": 42047,
    "index": 13,
    "start_time": 40486,
    "text": "- I think it leaves room for your dick"
  },
  {
    "end_time": 43814,
    "index": 14,
    "start_time": 42048,
    "text": "&#39;cause it&#39;s like really long in the front."
  },
  {
    "end_time": 44844,
    "index": 15,
    "start_time": 43814,
    "text": "- Worrying about one part"
  },
  {
    "end_time": 46702,
    "index": 16,
    "start_time": 44844,
    "text": "that dudes do not have to worry about,"
  },
  {
    "end_time": 48888,
    "index": 17,
    "start_time": 46702,
    "text": "which is the breasts."
  },
  {
    "end_time": 49358,
    "index": 18,
    "start_time": 48888,
    "text": "- I don&#39;t know."
  },
  {
    "end_time": 51100,
    "index": 19,
    "start_time": 49359,
    "text": "I don&#39;t know how to read boy sizes."
  },
  {
    "end_time": 53666,
    "index": 20,
    "start_time": 51100,
    "text": "It&#39;s just like 27, 32, 45."
  },
  {
    "end_time": 55697,
    "index": 21,
    "start_time": 53666,
    "text": "It&#39;s like, oh are we doing football plays?"
  },
  {
    "end_time": 57926,
    "index": 22,
    "start_time": 55698,
    "text": "- (scoffs indistinctly)."
  },
  {
    "end_time": 60513,
    "index": 23,
    "start_time": 57926,
    "text": "- Why would anyone want to\nwear this on their wedding day?"
  },
  {
    "end_time": 62836,
    "index": 24,
    "start_time": 60513,
    "text": "This is the the most uncomfortable thing."
  },
  {
    "end_time": 64888,
    "index": 25,
    "start_time": 62836,
    "text": "- I feel like I look like one of those"
  },
  {
    "end_time": 66958,
    "index": 26,
    "start_time": 64888,
    "text": "1930s big band singers."
  },
  {
    "end_time": 69368,
    "index": 27,
    "start_time": 66959,
    "text": "\u266b Hey man, won&#39;t you let the band play"
  },
  {
    "end_time": 71353,
    "index": 28,
    "start_time": 69368,
    "text": "\u266b Hey man, won&#39;t you let the band play \u266b"
  },
  {
    "end_time": 73366,
    "index": 29,
    "start_time": 71353,
    "text": "- Oh, I&#39;m not used to\nbuttoning all the buttons."
  },
  {
    "end_time": 77156,
    "index": 30,
    "start_time": 73367,
    "text": "(gasps) I feel like I&#39;m being suffocated."
  },
  {
    "end_time": 79820,
    "index": 31,
    "start_time": 77156,
    "text": "- This you should put in slow motion."
  },
  {
    "end_time": 80625,
    "index": 32,
    "start_time": 79820,
    "text": "Ahh."
  },
  {
    "end_time": 82176,
    "index": 33,
    "start_time": 80625,
    "text": "- There&#39;s so many things."
  },
  {
    "end_time": 85701,
    "index": 34,
    "start_time": 82176,
    "text": "I have no idea how to do this. (laughs)"
  },
  {
    "end_time": 87101,
    "index": 35,
    "start_time": 85701,
    "text": "This can&#39;t fit over my head."
  },
  {
    "end_time": 90314,
    "index": 36,
    "start_time": 87102,
    "text": "- (snorts) You guys wear these?"
  },
  {
    "end_time": 92604,
    "index": 37,
    "start_time": 90314,
    "text": "- Oh, fuck yeah!"
  },
  {
    "end_time": 94698,
    "index": 38,
    "start_time": 92605,
    "text": "Oh, hell yeah!"
  },
  {
    "end_time": 100321,
    "index": 39,
    "start_time": 97157,
    "text": "Okay, well it kinda looks\nlike I have a diaper on."
  },
  {
    "end_time": 103609,
    "index": 40,
    "start_time": 102230,
    "text": "- It&#39;s making me realize I really like"
  },
  {
    "end_time": 105850,
    "index": 41,
    "start_time": 103609,
    "text": "the woman&#39;s fit on my body."
  },
  {
    "end_time": 107336,
    "index": 42,
    "start_time": 105850,
    "text": "I prefer a tighter pant."
  },
  {
    "end_time": 109812,
    "index": 43,
    "start_time": 107336,
    "text": "- I always was like,\noh guys have it so easy"
  },
  {
    "end_time": 112551,
    "index": 44,
    "start_time": 109812,
    "text": "because suits are comfortable\nand they can move around,"
  },
  {
    "end_time": 114967,
    "index": 45,
    "start_time": 112552,
    "text": "and dresses are terrible\n&#39;cause you&#39;re basically like"
  },
  {
    "end_time": 117209,
    "index": 46,
    "start_time": 114967,
    "text": "stuck in one position all night."
  },
  {
    "end_time": 119170,
    "index": 47,
    "start_time": 117209,
    "text": "But suits are not comfortable."
  },
  {
    "end_time": 121828,
    "index": 48,
    "start_time": 119170,
    "text": "Guys have it bad in just\na different kind of way."
  },
  {
    "end_time": 124135,
    "index": 49,
    "start_time": 121828,
    "text": "- I guess I wasn&#39;t\ngiving guys enough credit"
  },
  {
    "end_time": 128979,
    "index": 50,
    "start_time": 124135,
    "text": "for how they were wearing tuxes\nand putting tuxes together"
  },
  {
    "end_time": 132137,
    "index": 51,
    "start_time": 128979,
    "text": "because this was more\nwork than I expected."
  },
  {
    "end_time": 141340,
    "index": 52,
    "start_time": 139469,
    "text": "- And it&#39;s got pockets!"
  },
  {
    "end_time": 144641,
    "index": 53,
    "start_time": 141340,
    "text": "- (grunts) Do I look like Count Dracula?"
  }
]