[
  {
    "end_time": 3866,
    "index": 1,
    "start_time": 709,
    "text": "And I need you now tonight"
  },
  {
    "end_time": 7571,
    "index": 2,
    "start_time": 4260,
    "text": "And I need you more than ever"
  },
  {
    "end_time": 11129,
    "index": 3,
    "start_time": 8070,
    "text": "And if you only hold me tight"
  },
  {
    "end_time": 15014,
    "index": 4,
    "start_time": 12020,
    "text": "We&#39;ll be holding on forever"
  },
  {
    "end_time": 19140,
    "index": 5,
    "start_time": 15539,
    "text": "And we&#39;ll only be making it right"
  },
  {
    "end_time": 22901,
    "index": 6,
    "start_time": 19513,
    "text": "Cuz we&#39;ll never be wrong forever"
  }
]