[
    {
        "index": 1,
        "start_time": 7058,
        "end_time": 11074,
        "text": "What could octopuses possibly\nhave in common with us?"
    },
    {
        "index": 2,
        "start_time": 11074,
        "end_time": 17014,
        "text": "After all, they don&#39;t have lungs, spines,\nor even a plural noun we can all agree on."
    },
    {
        "index": 3,
        "start_time": 17014,
        "end_time": 20162,
        "text": "But what they do have is the ability\nto solve puzzles,"
    },
    {
        "index": 4,
        "start_time": 20162,
        "end_time": 21998,
        "text": "learn through observation,"
    },
    {
        "index": 5,
        "start_time": 21998,
        "end_time": 23634,
        "text": "and even use tools,"
    },
    {
        "index": 6,
        "start_time": 23634,
        "end_time": 26112,
        "text": "just like some other animals we know."
    },
    {
        "index": 7,
        "start_time": 26112,
        "end_time": 29131,
        "text": "And what makes octopus intelligence\nso amazing"
    },
    {
        "index": 8,
        "start_time": 29131,
        "end_time": 31509,
        "text": "is that it comes \nfrom a biological structure"
    },
    {
        "index": 9,
        "start_time": 31509,
        "end_time": 34430,
        "text": "completely different from ours."
    },
    {
        "index": 10,
        "start_time": 34430,
        "end_time": 37074,
        "text": "The 200 or so species of octopuses"
    },
    {
        "index": 11,
        "start_time": 37074,
        "end_time": 40731,
        "text": "are mollusks \nbelonging to the order cephalopoda,"
    },
    {
        "index": 12,
        "start_time": 40731,
        "end_time": 42722,
        "text": "Greek for head-feet."
    },
    {
        "index": 13,
        "start_time": 42722,
        "end_time": 45707,
        "text": "Those heads contain impressively\nlarge brains,"
    },
    {
        "index": 14,
        "start_time": 45707,
        "end_time": 50458,
        "text": "with a brain to body ratio similar\nto that of other intelligent animals,"
    },
    {
        "index": 15,
        "start_time": 50458,
        "end_time": 55850,
        "text": "and a complex nervous system with\nabout as many neurons as that of a dog."
    },
    {
        "index": 16,
        "start_time": 55850,
        "end_time": 58136,
        "text": "But instead of being \ncentralized in the brain,"
    },
    {
        "index": 17,
        "start_time": 58136,
        "end_time": 64171,
        "text": "these 500 million neurons are spread out\nin a network of interconnected ganglia"
    },
    {
        "index": 18,
        "start_time": 64171,
        "end_time": 67580,
        "text": "organized into three basic structures."
    },
    {
        "index": 19,
        "start_time": 67580,
        "end_time": 71888,
        "text": "The central brain only contains\nabout 10% of the neurons,"
    },
    {
        "index": 20,
        "start_time": 71888,
        "end_time": 76670,
        "text": "while the two huge optic lobes\ncontain about 30%."
    },
    {
        "index": 21,
        "start_time": 76670,
        "end_time": 79398,
        "text": "The other 60% are in the tentacles,"
    },
    {
        "index": 22,
        "start_time": 79398,
        "end_time": 84366,
        "text": "which for humans would be like\nour arms having minds of their own."
    },
    {
        "index": 23,
        "start_time": 84366,
        "end_time": 86999,
        "text": "This is where things \nget even more interesting."
    },
    {
        "index": 24,
        "start_time": 86999,
        "end_time": 90869,
        "text": "Vertebrates like us have a rigid skeleton\nto support our bodies,"
    },
    {
        "index": 25,
        "start_time": 90869,
        "end_time": 92841,
        "text": "with joints that allow us to move."
    },
    {
        "index": 26,
        "start_time": 92841,
        "end_time": 95413,
        "text": "But not all types of movement are allowed."
    },
    {
        "index": 27,
        "start_time": 95413,
        "end_time": 97245,
        "text": "You can&#39;t bend your knee backwards,"
    },
    {
        "index": 28,
        "start_time": 97245,
        "end_time": 100136,
        "text": "or bend your forearm in the middle,\nfor example."
    },
    {
        "index": 29,
        "start_time": 100136,
        "end_time": 103665,
        "text": "Cephalopods, on the other hand,\nhave no bones at all,"
    },
    {
        "index": 30,
        "start_time": 103665,
        "end_time": 108339,
        "text": "allowing them to bend their limbs\nat any point and in any direction."
    },
    {
        "index": 31,
        "start_time": 108339,
        "end_time": 109638,
        "text": "So shaping their tentacles"
    },
    {
        "index": 32,
        "start_time": 109638,
        "end_time": 113785,
        "text": "into any one of the virtually \nlimitless number of possible arrangements"
    },
    {
        "index": 33,
        "start_time": 113785,
        "end_time": 116739,
        "text": "is unlike anything we are used to."
    },
    {
        "index": 34,
        "start_time": 116739,
        "end_time": 120694,
        "text": "Consider a simple task,\nlike grabbing and eating an apple."
    },
    {
        "index": 35,
        "start_time": 120694,
        "end_time": 124348,
        "text": "The human brain contains a neurological\nmap of our body."
    },
    {
        "index": 36,
        "start_time": 124348,
        "end_time": 125473,
        "text": "When you see the apple,"
    },
    {
        "index": 37,
        "start_time": 125473,
        "end_time": 129226,
        "text": "your brain&#39;s motor center activates\nthe appropriate muscles,"
    },
    {
        "index": 38,
        "start_time": 129226,
        "end_time": 131310,
        "text": "allowing you to reach out with your arm,"
    },
    {
        "index": 39,
        "start_time": 131310,
        "end_time": 132852,
        "text": "grab it with your hand,"
    },
    {
        "index": 40,
        "start_time": 132852,
        "end_time": 134265,
        "text": "bend your elbow joint,"
    },
    {
        "index": 41,
        "start_time": 134265,
        "end_time": 135870,
        "text": "and bring it to your mouth."
    },
    {
        "index": 42,
        "start_time": 135870,
        "end_time": 138666,
        "text": "For an octopus, \nthe process is quite different."
    },
    {
        "index": 43,
        "start_time": 138666,
        "end_time": 140465,
        "text": "Rather than a body map,"
    },
    {
        "index": 44,
        "start_time": 140465,
        "end_time": 143898,
        "text": "the cephalopod brain \nhas a behavior library."
    },
    {
        "index": 45,
        "start_time": 143898,
        "end_time": 146013,
        "text": "So when an octopus sees food,"
    },
    {
        "index": 46,
        "start_time": 146013,
        "end_time": 148905,
        "text": "its brain doesn&#39;t activate \na specific body part,"
    },
    {
        "index": 47,
        "start_time": 148905,
        "end_time": 152473,
        "text": "but rather a behavioral response to grab."
    },
    {
        "index": 48,
        "start_time": 152473,
        "end_time": 154556,
        "text": "As the signal travels through the network,"
    },
    {
        "index": 49,
        "start_time": 154556,
        "end_time": 156990,
        "text": "the arm neurons pick up the message"
    },
    {
        "index": 50,
        "start_time": 156990,
        "end_time": 159724,
        "text": "and jump into action \nto command the movement."
    },
    {
        "index": 51,
        "start_time": 159724,
        "end_time": 161877,
        "text": "As soon as the arm touches the food,"
    },
    {
        "index": 52,
        "start_time": 161877,
        "end_time": 166535,
        "text": "a muscle activation wave travels\nall the way through the arm to its base,"
    },
    {
        "index": 53,
        "start_time": 166535,
        "end_time": 170709,
        "text": "while the arm sends back another wave\nfrom the base to the tip."
    },
    {
        "index": 54,
        "start_time": 170709,
        "end_time": 174400,
        "text": "The signals meet halfway\nbetween the food and the base of the arm,"
    },
    {
        "index": 55,
        "start_time": 174400,
        "end_time": 177343,
        "text": "letting it know to bend at that spot."
    },
    {
        "index": 56,
        "start_time": 177343,
        "end_time": 181591,
        "text": "What all this means is that each\nof an octopus&#39;s eight arms"
    },
    {
        "index": 57,
        "start_time": 181591,
        "end_time": 184092,
        "text": "can essentially think for itself."
    },
    {
        "index": 58,
        "start_time": 184092,
        "end_time": 186825,
        "text": "This gives it amazing flexibility \nand creativity"
    },
    {
        "index": 59,
        "start_time": 186825,
        "end_time": 189644,
        "text": "when facing a new situation or problem,"
    },
    {
        "index": 60,
        "start_time": 189644,
        "end_time": 191702,
        "text": "whether its opening \na bottle to reach food,"
    },
    {
        "index": 61,
        "start_time": 191702,
        "end_time": 193436,
        "text": "escaping through a maze,"
    },
    {
        "index": 62,
        "start_time": 193436,
        "end_time": 195359,
        "text": "moving around in a new environment,"
    },
    {
        "index": 63,
        "start_time": 195359,
        "end_time": 199601,
        "text": "changing the texture and the color\nof its skin to blend into the scenery,"
    },
    {
        "index": 64,
        "start_time": 199601,
        "end_time": 203648,
        "text": "or even mimicking other creatures\nto scare away enemies."
    },
    {
        "index": 65,
        "start_time": 203648,
        "end_time": 206477,
        "text": "Cephalopods may have evolved \ncomplex brains"
    },
    {
        "index": 66,
        "start_time": 206477,
        "end_time": 209170,
        "text": "long before our vertebrate relatives."
    },
    {
        "index": 67,
        "start_time": 209170,
        "end_time": 212959,
        "text": "And octopus intelligence isn&#39;t just useful\nfor octopuses."
    },
    {
        "index": 68,
        "start_time": 212959,
        "end_time": 217774,
        "text": "Their radically different nervous system\nand autonomously thinking appendages"
    },
    {
        "index": 69,
        "start_time": 217774,
        "end_time": 219572,
        "text": "have inspired new research"
    },
    {
        "index": 70,
        "start_time": 219572,
        "end_time": 223944,
        "text": "in developing flexible robots\nmade of soft materials."
    },
    {
        "index": 71,
        "start_time": 223944,
        "end_time": 228882,
        "text": "And studying how intelligence can arise\nalong such a divergent evolutionary path"
    },
    {
        "index": 72,
        "start_time": 228882,
        "end_time": 234056,
        "text": "can help us understand more about\nintelligence and consciousness in general."
    },
    {
        "index": 73,
        "start_time": 234056,
        "end_time": 237483,
        "text": "Who knows what other forms \nof intelligent life are possible,"
    },
    {
        "index": 74,
        "start_time": 237483,
        "end_time": 240791,
        "text": "or how they process the world around them."
    }
]